llama_index/readers/pathway/__init__.py
llama_index/readers/pathway/base.py
llama_index_readers_pathway-0.4.1.dist-info/METADATA
llama_index_readers_pathway-0.4.1.dist-info/WHEEL
llama_index_readers_pathway-0.4.1.dist-info/licenses/LICENSE
llama_index_readers_pathway-0.4.1.dist-info/RECORD
